{
    "token": {
        "type": "INPUT_NODE",
        "hierarchy": 0
    },
    "kento": {
        "type": "OUTPUT_NODE",
        "hierarchy": -1
    },
    "multiplier_1": {
        "type": "BLOCK",
        "block_type": "MULTIPLIER",
        "inputs": [
            "(token",
            "5) / 2"
        ],
        "output": "multiplier_1",
        "hierarchy": 1
    },
    "wire_1": {
        "type": "WIRE",
        "from": "multiplier_1",
        "to": "kyoto",
        "hierarchy": 2
    },
    "constant_0": {
        "type": "CONSTANT",
        "value": 0,
        "hierarchy": 0
    },
    "wire_2": {
        "type": "WIRE",
        "from": "constant_0",
        "to": "kyoto",
        "hierarchy": 2
    },
    "comparator_1": {
        "type": "BLOCK",
        "block_type": "COMPARATOR",
        "condition": "kyoto < 0",
        "true_path": "-1",
        "false_path": null,
        "output": "kento",
        "hierarchy": 2
    },
    "constant_1": {
        "type": "CONSTANT",
        "value": 1,
        "hierarchy": 0
    },
    "comparator_2": {
        "type": "BLOCK",
        "block_type": "COMPARATOR",
        "condition": "kyoto > 0",
        "true_path": "constant_1",
        "false_path": null,
        "output": "kento",
        "hierarchy": 2
    }
}